opentouch/__init__.py
opentouch/core/__init__.py
opentouch/core/base_cnn.py
opentouch/core/base_filter.py
opentouch/core/base_model.py
opentouch/core/base_nn.py
opentouch/core/model_loader.py
opentouch_interface/__init__.py
opentouch_interface/decoder.py
opentouch_interface/core/__init__.py
opentouch_interface/core/oti_config.py
opentouch_interface/core/payload.py
opentouch_interface/core/sensor_factory.py
opentouch_interface/core/sensor_group.py
opentouch_interface/core/sensor_group_saver.py
opentouch_interface/core/dataclasses/__init__.py
opentouch_interface/core/dataclasses/nested_sensor_data.py
opentouch_interface/core/registries/__init__.py
opentouch_interface/core/registries/central_registry.py
opentouch_interface/core/registries/class_registries.py
opentouch_interface/core/registries/model_registry.py
opentouch_interface/core/registries/sensor_group_registry.py
opentouch_interface/core/registries/viewer_group_registry.py
opentouch_interface/core/sensors/__init__.py
opentouch_interface/core/sensors/digit.py
opentouch_interface/core/sensors/digit360.py
opentouch_interface/core/sensors/gelsight_mini.py
opentouch_interface/core/sensors/touch_sensor.py
opentouch_interface/core/sensors/interfaces/__init__.py
opentouch_interface/core/sensors/interfaces/digit360_interface.py
opentouch_interface/core/sensors/interfaces/digit_interface.py
opentouch_interface/core/sensors/interfaces/gelsight_interface.py
opentouch_interface/core/serialization/__init__.py
opentouch_interface/core/serialization/base_serializer.py
opentouch_interface/core/serialization/digit360_serializer.py
opentouch_interface/core/serialization/digit_sensor_serializer.py
opentouch_interface/core/serialization/gelsight_mini_serializer.py
opentouch_interface/core/validation/__init__.py
opentouch_interface/core/validation/sensor_config.py
opentouch_interface/core/validation/touch_sensor_config.py
opentouch_interface/core/validation/validator.py
opentouch_interface/core/validation/sensors/__init__.py
opentouch_interface-0.2.0.dist-info/licenses/LICENSE
opentouch_interface-0.2.0.dist-info/METADATA
opentouch_interface-0.2.0.dist-info/WHEEL
opentouch_interface-0.2.0.dist-info/entry_points.txt
opentouch_interface-0.2.0.dist-info/top_level.txt
opentouch_interface-0.2.0.dist-info/RECORD
