Metadata-Version: 2.4
Name: opentouch-interface
Version: 0.2.0
Summary: Interface to connect to touch sensors
Home-page: https://github.com/lasr-lab/opentouch-interface
Author: Roberto Calandra
Author-email: rcalandra@lasr.org
Classifier: Programming Language :: Python :: 3.8
Classifier: License :: OSI Approved :: MIT License
Classifier: Operating System :: POSIX :: Linux
Classifier: Programming Language :: Python :: 3 :: Only
Requires-Python: >=3.10
License-File: LICENSE
Requires-Dist: streamlit
Requires-Dist: numpy
Requires-Dist: h5py
Requires-Dist: PyYAML
Requires-Dist: hydra-core
Requires-Dist: omegaconf
Requires-Dist: matplotlib
Requires-Dist: packaging
Requires-Dist: decorator
Requires-Dist: pydantic
Requires-Dist: opencv-python
Requires-Dist: streamlit_code_editor
Requires-Dist: onnxruntime
Requires-Dist: cobs
Requires-Dist: torch
Requires-Dist: pyudev
Requires-Dist: betterproto
Requires-Dist: pyserial
Requires-Dist: sounddevice
Requires-Dist: pandas
Requires-Dist: altair
Requires-Dist: onnx
Dynamic: author
Dynamic: author-email
Dynamic: classifier
Dynamic: description
Dynamic: description-content-type
Dynamic: home-page
Dynamic: license-file
Dynamic: requires-dist
Dynamic: requires-python
Dynamic: summary
